faonet/__init__.py
faonet/export.py
faonet/filtering.py
faonet/fitting.py
faonet/io.py
faonet/metrics.py
faonet/network.py
faonet/plots.py
faonet-0.1.0.dist-info/licenses/LICENSE
faonet-0.1.0.dist-info/METADATA
faonet-0.1.0.dist-info/WHEEL
faonet-0.1.0.dist-info/top_level.txt
faonet-0.1.0.dist-info/RECORD
