Metadata-Version: 2.4
Name: faonet
Version: 0.1.0
Summary: Analyze bipartite trade networks using FAOSTAT data
Author-email: Javier Galeano <galeanojav@gmail.com>
License-Expression: MIT
Project-URL: Homepage, https://github.com/galeanojav/FAONet
Project-URL: Documentation, https://galeanojav.github.io/FAONet
Classifier: Development Status :: 3 - Alpha
Classifier: Intended Audience :: Science/Research
Classifier: Programming Language :: Python :: 3
Classifier: Topic :: Scientific/Engineering :: Information Analysis
Requires-Python: >=3.8
License-File: LICENSE
Requires-Dist: pandas
Requires-Dist: networkx
Requires-Dist: matplotlib
Requires-Dist: seaborn
Dynamic: license-file
